core/__init__.py
core/protocol.py
core/server.py
ember_chat-0.1.0.dist-info/licenses/LICENSE
plugins/__init__.py
plugins/admin_plugin.py
plugins/auth_plugin.py
plugins/http_file_share.py
plugins/logger_plugin.py
plugins/tcp_transport.py
plugins/websocket_ui.py
ember_chat-0.1.0.dist-info/METADATA
ember_chat-0.1.0.dist-info/WHEEL
ember_chat-0.1.0.dist-info/entry_points.txt
ember_chat-0.1.0.dist-info/top_level.txt
ember_chat-0.1.0.dist-info/RECORD
