Metadata-Version: 2.4
Name: ember-chat
Version: 0.1.0
Summary: Simple, open and extensible chat server with plugin system
Author-email: sipm1ner <kirillbelakov2222@gmail.com>
License-Expression: MIT
Project-URL: Homepage, https://github.com/supminer/emberchat
Project-URL: Repository, https://github.com/supminer/emberchat
Classifier: Development Status :: 4 - Beta
Classifier: Intended Audience :: Developers
Classifier: Programming Language :: Python :: 3
Classifier: Programming Language :: Python :: 3.8
Classifier: Programming Language :: Python :: 3.9
Classifier: Programming Language :: Python :: 3.10
Classifier: Programming Language :: Python :: 3.11
Classifier: Programming Language :: Python :: 3.12
Classifier: Programming Language :: Python :: 3.13
Classifier: Operating System :: OS Independent
Classifier: Topic :: Communications :: Chat
Classifier: Topic :: Internet
Requires-Python: >=3.8
License-File: LICENSE
Requires-Dist: websockets>=12.0
Requires-Dist: pyyaml>=6.0
Dynamic: license-file
